parashu/__init__.py
parashu-0.1.0.dist-info/LICENSE
parashu-0.1.0.dist-info/METADATA
parashu-0.1.0.dist-info/WHEEL
parashu-0.1.0.dist-info/RECORD
