Metadata-Version: 2.3
Name: parashu
Version: 0.1.0
Summary: A modular agent orchestration platform
Author: Chirag Juneja
Author-email: chiragjuneja6@gmail.com
Requires-Python: >=3.13
Classifier: Programming Language :: Python :: 3
Classifier: Programming Language :: Python :: 3.13
